[
    {
        "pubdate": "2024-12-12T10:37:49.000Z",
        "arcurl": "http://www.bilibili.com/video/av113639398907314",
        "author": "高天天天翔",
        "title": "你相信异地恋凌晨3点的我想你吗？",
        "typename": "短片",
        "description": "-",
        "tag": "爱情,青春,恋爱,我在B站拍短剧"
    },
    {
        "pubdate": "2024-12-12T10:00:00.000Z",
        "arcurl": "http://www.bilibili.com/video/av113638476087864",
        "author": "小片片说大片",
        "title": "亲爹和亲女儿是同龄人？反转不断，烧脑追凶，这剧怎么没人安利？！《太阳星辰》",
        "typename": "影视杂谈",
        "description": "“新港剧”怎么拍？看《太阳星辰》就知道了。\n陈伟霆化作时空警察，穿越到25年后追凶，九十年代的意外火灾和连环杀人大案竟然藏着延续多年的秘密。\n层层反转，细节满满，演到最后还不烂尾，为啥这剧反而没人看？",
        "tag": "穿越,悬疑,犯罪,刑侦,探案,陈伟霆,平行时空,刘雅瑟,太阳星辰,2024影娱亿点好活"
    },
    {
        "pubdate": "2024-12-12T09:00:00.000Z",
        "arcurl": "http://www.bilibili.com/video/av113638862032841",
        "author": "开心嘴炮",
        "title": "杨子的五个手机都不如它！《小岛电影院》真正属于每个人的大片",
        "typename": "影视杂谈",
        "description": "《小岛电影院》趣味解说",
        "tag": "电影,李行亮,杨子,留几手,再见爱人,麦琳,华为Mate 70 Pro,Mate本色如初,用红枫准没错,小岛电影院"
    },
    {
        "pubdate": "2024-12-12T08:25:57.000Z",
        "arcurl": "https://b23.tv/BV1L4qhYjEmc",
        "author": "ご光影的故事ご",
        "title": "拼到弹尽粮绝！石宇奇大心脏惊人逆转昆拉武特！2024年世界羽联总决赛",
        "typename": "竞技体育",
        "description": "第一局的石头打的有点心急，想要通过高质量的进攻，直接打出机会，但是粘球的昆不但打不死，还会打出防反，，而到了第二局，石头重新稳下心态，将昆的注意力带到了网前，昆果真上了套，然后石头的网前手法，就开始发挥了优势，到了第三局，昆的恢复能力占了上分，一度拉开了比分，石头体能严重瓶颈，但是转折点就在两人降速的拉开上，昆是一点便宜没有占到不说，石头还恢复了过来，而且关键分的处理上，石头各种大心脏，简直是绝了，敢打敢拼，石头还是那个石头，恭喜石头拿下这个来之不易的逆转吧 \n粉丝群暗号：光影我要聊球\n25群：10116",
        "tag": ""
    },
    {
        "pubdate": "2024-12-12T03:27:25.000Z",
        "arcurl": "http://www.bilibili.com/video/av113637687565520",
        "author": "北斗导航Compass",
        "title": "为什么我回答不了观众的学业和就业问题",
        "typename": "校园学习",
        "description": "",
        "tag": "高校,找工作,学业,问题,研究生,求职,观众,就业,考研,读博"
    },
    {
        "pubdate": "2024-12-12T01:47:46.000Z",
        "arcurl": "http://www.bilibili.com/video/av113637318463294",
        "author": "一只吐槽圆",
        "title": "【2024十大综艺名场面】爆笑盘点",
        "typename": "娱乐杂谈",
        "description": "1.你们麦麸麦的太严重了《亚洲超星团》\n2.难为把你们一个个搜罗起来《新说唱2024》\n3.乘风破音的姐姐《乘风2024》\n4.憨披斩棘的哥哥《披荆斩棘4》\n5.张雨绮对你提出点名批评《脱口秀和ta的朋友们》\n6.《小品2024》《歌手2024》\n7.以为在看宫斗剧！《十天之后回到现实》\n8.以为在看黑暗荣耀！《花儿与少年6》\n9.演员是最低级的职业吗？《无限超越班2》\n10.再爱见人《再见爱人4》",
        "tag": "歌手,那英,周雨彤,花少,再见爱人,浪姐,披荆斩棘的哥哥,麦琳,无限超越班,2024影娱亿点好活"
    },
    {
        "pubdate": "2024-12-11T16:27:12.000Z",
        "arcurl": "http://www.bilibili.com/video/av113635020051203",
        "author": "水遁溜了溜了",
        "title": "朱帅臣 2024-12-11",
        "typename": "日常",
        "description": "",
        "tag": "直播,录屏,拒绝,山西,连麦,北斗导航compass,朱帅臣,爱的100种表达方式,生活万花筒16.0"
    },
    {
        "pubdate": "2024-12-11T14:39:52.000Z",
        "arcurl": "http://www.bilibili.com/video/av113634701348354",
        "author": "快快超爱笑2020",
        "title": "小小圣诞树精朝我做鬼脸了",
        "typename": "亲子",
        "description": "-",
        "tag": "可爱,记录"
    },
    {
        "pubdate": "2024-12-11T13:24:40.000Z",
        "arcurl": "http://www.bilibili.com/video/av113634382450744",
        "author": "糖果果的未来要发光",
        "title": "女生坦白局：说出来会“遭白眼”的爱好……",
        "typename": "日常",
        "description": "拉着小伙伴聊了下各自的兴趣爱好，聊完后发现原来我们热爱的世界这么美好～\n\n小的时候只知道学习，任何兴趣爱好都没有，博士的时候偶然看了一些剧，现在工作了，经常觉得兴趣爱好多么重要，也经常羡慕有兴趣爱好的人。\n\n我觉得兴趣是对平凡日子最诗意的抵抗，大家有什么兴趣爱好呢？",
        "tag": "爱情,女生,感情,KPOP,兴趣,爱好,生活记录,坦白局,谷子经济,爱的100种表达方式,生活万花筒16.0"
    },
    {
        "pubdate": "2024-12-11T11:15:50.000Z",
        "arcurl": "https://b23.tv/BV1wsqUYkE1f",
        "author": "波士顿圆脸",
        "title": "以色列趁叙利亚局势混乱吞并戈兰高地 美国：理解支持",
        "typename": "环球",
        "description": "",
        "tag": "百万播放"
    },
    {
        "pubdate": "2024-12-11T11:00:00.000Z",
        "arcurl": "https://b23.tv/BV16XqSY3E4M",
        "author": "Jason-老湿",
        "title": "五月天阿信再遭质疑？他的唱功属于什么水平？阿信唱功解析！",
        "typename": "乐评盘点",
        "description": "╔═════════════════╗\n╠学唱歌请看评论区置顶链接 ╣\n╚═════════════════╝",
        "tag": ""
    },
    {
        "pubdate": "2024-12-11T10:00:00.000Z",
        "arcurl": "https://b23.tv/BV1M5qUYEEoa",
        "author": "雷三杯",
        "title": "他不识谱不会乐器，却在40岁前写下这些经典歌曲，63岁出新专辑依然充满讽刺批判",
        "typename": "乐评盘点",
        "description": "有人说每个走过90年代的人，心中都有一首郑智化。如今暌违26年再出专辑，让我们从1988年开始回顾他36年的音乐历程……",
        "tag": ""
    },
    {
        "pubdate": "2024-12-11T03:00:00.000Z",
        "arcurl": "http://www.bilibili.com/video/av113629449952784",
        "author": "铁铁铁柱_",
        "title": "2024烂剧颁奖典礼，今年怎么这么多笑料啊【铁柱】",
        "typename": "影视杂谈",
        "description": "每年我最开心的时候到了！相信你们也是！",
        "tag": "吐槽,爆笑,电视剧,盘点,颁奖典礼,烂剧,2024,2024影娱亿点好活,烂剧颁奖"
    },
    {
        "pubdate": "2024-12-11T02:21:41.000Z",
        "arcurl": "http://www.bilibili.com/video/av113631782051054",
        "author": "三代鹿人",
        "title": "2024年度十大烂片盘点！没有最烂只有更烂，今年最抽象的电影都在这了！",
        "typename": "影视杂谈",
        "description": "2024年度金拖把颁奖典礼 · 国产烂片 TOP 10 （上） \n- \n本期点赞过3万，我将火速更新下半场。听说现在关注的以后都是尊贵的老纯鹿人啦，\n我们下期再见 :D",
        "tag": "搞笑,烂片,颁奖,年终盘点,退钱,金拖把奖,2024影娱亿点好活"
    },
    {
        "pubdate": "2024-12-10T16:17:41.000Z",
        "arcurl": "http://www.bilibili.com/video/av113629366129570",
        "author": "水遁溜了溜了",
        "title": "朱帅臣 有点亢奋 在隔壁的幸福生活 北斗导航compass",
        "typename": "日常",
        "description": "",
        "tag": "快乐,直播,记录,幼儿园,录屏,直播录像,生活记录,桌游棋牌,北斗导航compass,爱的100种表达方式,生活万花筒16.0"
    },
    {
        "pubdate": "2024-12-10T13:31:10.000Z",
        "arcurl": "https://b23.tv/BV1dTqCYmEyY",
        "author": "探谜",
        "title": "神奇的软柄锤，锤柄明明是软的，却比普通铁锤更加实用？",
        "typename": "科学科普",
        "description": "神奇的软柄锤，锤柄明明是软的，却比普通铁锤更加实用？",
        "tag": ""
    },
    {
        "pubdate": "2024-12-10T12:25:15.000Z",
        "arcurl": "http://www.bilibili.com/video/av113628510425114",
        "author": "米粒粒儿-",
        "title": "20后女儿每天都要哄爸爸玩～",
        "typename": "亲子",
        "description": "-",
        "tag": "治愈,可爱,爸爸,女儿,萌娃,生活记录,100种带娃生活,我们的家庭日记11.0"
    },
    {
        "pubdate": "2024-12-10T10:21:23.000Z",
        "arcurl": "http://www.bilibili.com/video/av113628007106404",
        "author": "小片片说大片",
        "title": "全程荒诞！绑架线人玩赌命游戏，深夜查案找按摩女郎？国产刑侦剧《白夜破晓》第六案",
        "typename": "影视杂谈",
        "description": "一名保安离奇死亡，浑身遍布伤痕，身上只剩下内衣。\n他是怎么死的？凶手的动机是什么？\n咱们今天继续来看，《白夜破晓》的第六案——《保安遇害案》。",
        "tag": "悬疑,犯罪,潘粤明,刑侦,探案,梁缘,王龙正,白夜破晓,2024影娱亿点好活"
    },
    {
        "pubdate": "2024-12-10T09:30:00.000Z",
        "arcurl": "http://www.bilibili.com/video/av113627604456436",
        "author": "虫哥说电影",
        "title": "普通人用手机拍出的大片！人类只剩下意识数据，那人生还有意义吗？",
        "typename": "影视杂谈",
        "description": "第一篇《生活的倒影》，讲述的是一个特殊学校里需要关爱的孩子们的故事。第二篇《黑河》是大学生拍摄的末日科幻大片。\n这两部短片都用华为手机完成拍摄的。",
        "tag": "青春,生活,科幻,现实,华为,微电影,金鸡,电影解说,华为影像金鸡手机电影计划,年轻人的奥斯卡"
    },
    {
        "pubdate": "2024-12-10T04:22:08.000Z",
        "arcurl": "http://www.bilibili.com/video/av113626597886349",
        "author": "刘老师说电影",
        "title": "2024国产烂片爆笑盘点，暨第八届中国电影金菊花颁奖典礼！",
        "typename": "影视杂谈",
        "description": "往年精彩回顾：\n第七届：BV1zb4y1376w\n第六届：BV1yM41117KQ\n第五届：BV1XP4y1n74P\n第四届：BV1Bi4y1w74B \n第三届：BV1oJ411W7AL \n第二届：BV1Jt411r7oa \n第一届：BV17W411b74U",
        "tag": "国产,电影,烂片,国产电影,盘点,颁奖典礼,年终盘点,金菊花,2024影娱亿点好活,2024影剧综颁奖典礼"
    },
    {
        "pubdate": "2024-12-09T12:41:06.000Z",
        "arcurl": "http://www.bilibili.com/video/av113622906837554",
        "author": "米粒粒儿-",
        "title": "这大眼睛白长了～也不好使啊～",
        "typename": "亲子",
        "description": "-",
        "tag": "可爱,女儿,萌娃,生活记录,100种带娃生活,我们的家庭日记11.0"
    },
    {
        "pubdate": "2024-12-09T11:48:00.000Z",
        "arcurl": "http://www.bilibili.com/video/av113622688798154",
        "author": "可妈可吗",
        "title": "30多万装修白送房东？到底是冤大头还是真香？租房怎么签？",
        "typename": "家居房产",
        "description": "",
        "tag": "装修,房产,租房,合同,租房改造,租房合同,我们住在B站,B站家人大扩列"
    },
    {
        "pubdate": "2024-12-09T10:42:26.000Z",
        "arcurl": "https://b23.tv/BV1ZLqKY2EiP",
        "author": "奥林匹克运动会",
        "title": "🥌：纵享丝滑人生",
        "typename": "竞技体育",
        "description": "你了解冰壶吗？",
        "tag": ""
    },
    {
        "pubdate": "2024-12-09T10:19:50.000Z",
        "arcurl": "",
        "author": "丶月神大人丶",
        "title": "",
        "typename": "",
        "description": "",
        "tag": ""
    },
    {
        "pubdate": "2024-12-09T10:00:00.000Z",
        "arcurl": "http://www.bilibili.com/video/av113620826460005",
        "author": "小片片说大片",
        "title": "精妙骗局，连环反转，一场高智商复仇，靠画头骨断案！《猎罪图鉴》第四案",
        "typename": "影视杂谈",
        "description": "继续看《猎罪图鉴》第四案：富家女绑架案。",
        "tag": "悬疑,犯罪,刑侦,探案,檀健次,金世佳,猎罪图鉴,人人都能聊影视"
    },
    {
        "pubdate": "2024-12-09T09:30:00.000Z",
        "arcurl": "http://www.bilibili.com/video/av113605173315549",
        "author": "话很多的小姐姐们",
        "title": "2024内鱼十大喜剧人：有人抽象有人疯！靠着天赋往前冲！",
        "typename": "娱乐杂谈",
        "description": "让我们有请2024年获奖的喜剧人出场：\n万妮达·浓妆只是她搞笑女的面具\n焦迈奇·文艺男是我对你最大的误解\n李耕耘·不仅全盘托出 还把盘子咬碎了\n曹恩齐·仙子不下凡 只堕魔\n丁禹兮·无情的接梗机器\n王安宇·完蛋了是五阿呆啊\n那英·57岁正是口无遮拦的年纪\n纪凌尘·人怎么可以自信成这样\n向佐·永远莫名其妙\n黄子韬·易燃易爆炸",
        "tag": "搞笑,娱乐,那英,抽象,黄子韬,喜剧人,向佐,万妮达,丁禹兮,王安宇"
    },
    {
        "pubdate": "2024-12-09T01:58:43.000Z",
        "arcurl": "http://www.bilibili.com/video/av113620373471938",
        "author": "bili_59465841376",
        "title": "【张踩铃】【脱口秀】我在家庭里体会流浪地球的困境",
        "typename": "综艺",
        "description": "【张踩铃】【脱口秀】我在家庭里体会流浪地球的困境",
        "tag": "吐槽,搞笑,爆笑,脱口秀,吐槽大会,流浪地球,困境,傅首尔"
    },
    {
        "pubdate": "2024-12-08T11:47:08.000Z",
        "arcurl": "http://www.bilibili.com/video/av113616984478901",
        "author": "动物园会议",
        "title": "【年终盘点】2024“鸭叫之夜”内娱颁奖典礼！",
        "typename": "娱乐杂谈",
        "description": "",
        "tag": "盘点,杨幂,名场面,黄子韬,柯学,范丞丞,麦学,花学,2024影娱亿点好活,春山学"
    },
    {
        "pubdate": "2024-12-08T11:06:22.000Z",
        "arcurl": "http://www.bilibili.com/video/av113616816773442",
        "author": "岱川博士",
        "title": "岱川博士: 西方人眼中的儒家礼仪-由中国民俗小仪式联想到的…",
        "typename": "社科·法律·心理",
        "description": "-",
        "tag": "哲学,英语,父母,传统文化,家庭教育,玄学,育儿,外国人在中国,克己复礼,国学文化"
    },
    {
        "pubdate": "2024-12-08T09:30:00.000Z",
        "arcurl": "https://b23.tv/BV1hiqJY6Edz",
        "author": "兔叭咯",
        "title": "【医学博士】如何快速瘦肚子？| 三个“好”习惯，“摧毁”你的肝！",
        "typename": "科学科普",
        "description": "为什么有人四肢纤细却肚子很胖？\n本期视频带你深扒内脏脂肪的真相！\n从内脏脂肪的危害到那些意想不到的“毁肝”行为！\n再到缓解脂肪肝的小技巧~\n科学减脂，保护肝脏！\npeace~\n您可能还喜欢：\n【打呼噜】BV1GfUSY4EoQ\n【精神病】BV1T6mfYqEKh\n【异食癖】BV12kDoYMEQR\n【脑额叶手术】BV1VzSoY7EeH\n【尿毒症】BV1xnyDYqEmA",
        "tag": "百万播放"
    },
    {
        "pubdate": "2024-12-08T09:00:00.000Z",
        "arcurl": "https://b23.tv/BV1F6qnYoEz1",
        "author": "盘点音乐2023",
        "title": "用50首歌带你回顾2018-2023年，旋律响起勾起了多少人的回忆！",
        "typename": "乐评盘点",
        "description": "",
        "tag": ""
    },
    {
        "pubdate": "2024-12-08T09:00:00.000Z",
        "arcurl": "http://www.bilibili.com/video/av113615726186998",
        "author": "虫哥说电影",
        "title": "找黄磊做闺蜜是啥体验？《我爱男闺蜜》一部有趣的都市喜剧。十多年前黄磊就在显摆厨艺了~",
        "typename": "影视杂谈",
        "description": "这部剧还是非常有趣的。没想到黄磊很早以前就在显摆自己的厨艺啦~~~",
        "tag": "爱情,童年,搞笑,喜剧,回忆杀,陈数,黄磊,黄小厨,人人都能聊影视,敌蜜,人人都能聊影视4.0"
    },
    {
        "pubdate": "2024-12-08T08:41:04.000Z",
        "arcurl": "http://www.bilibili.com/video/av113616246282912",
        "author": "北斗导航Compass",
        "title": "疫情放开两周年纪念——我们人人都是赛博史官",
        "typename": "日常",
        "description": "",
        "tag": "回忆,工作,记录,年终总结,生活记录,疫情,新冠"
    },
    {
        "pubdate": "2024-12-08T04:02:08.000Z",
        "arcurl": "http://www.bilibili.com/video/av113615206089000",
        "author": "快快超爱笑2020",
        "title": "小丑：小孩 我将毕生所学都教给你了",
        "typename": "亲子",
        "description": "-",
        "tag": "养娃二三事,我们的家庭日记11.0"
    },
    {
        "pubdate": "2024-12-08T03:38:33.000Z",
        "arcurl": "http://www.bilibili.com/video/av113615105432353",
        "author": "三代鹿人",
        "title": "麦琳杨子互换剧本？李行亮下跪求婚？这节目真能恶心人！【再见爱人4】",
        "typename": "娱乐杂谈",
        "description": "从《与麦同行》到《麦琳的浪漫旅行》，我从来没见过这么膈应人的爱情！",
        "tag": "黄圣依,李行亮,杨子,牧神记,妻子的浪漫旅行,麦琳,他超爱,动画种草激励计划,再见爱人4,葛夕,动画种草激励计划7.0"
    },
    {
        "pubdate": "2024-12-07T11:44:26.000Z",
        "arcurl": "http://www.bilibili.com/video/av113611347333009",
        "author": "托马斯家的",
        "title": "女友为了让我晚上和她一起睡，也是拼了…",
        "typename": "日常",
        "description": "-",
        "tag": "原创,爱情,搞笑,女友,小姐姐,爱的100种表达方式,生活万花筒16.0"
    },
    {
        "pubdate": "2024-12-07T10:00:00.000Z",
        "arcurl": "http://www.bilibili.com/video/av113605978621942",
        "author": "RICH徐大花",
        "title": "阿B新短剧《老盔有了新主人》这个赛道真是越来越卷了",
        "typename": "影视杂谈",
        "description": "",
        "tag": "短剧,影评杂谈,老盔有了新主人"
    },
    {
        "pubdate": "2024-12-07T09:00:00.000Z",
        "arcurl": "http://www.bilibili.com/video/av113605827627264",
        "author": "话很多的小姐姐们",
        "title": "《蜀锦人家》：让你们搞CP没让你们演小品啊！",
        "typename": "影视杂谈",
        "description": "搞钱系列终于轮到我们川渝地区了！",
        "tag": "搞笑,电视剧,古装,谭松韵,经超,郑业成,影视杂谈,陈小纭,搞钱,蜀锦人家"
    },
    {
        "pubdate": "2024-12-07T02:10:00.000Z",
        "arcurl": "http://www.bilibili.com/video/av113606733598706",
        "author": "开心嘴炮",
        "title": "杨子麦琳是正缘的四大理由！我从没嗑过这么难嗑的糖！《再见爱人》高能解说",
        "typename": "娱乐杂谈",
        "description": "《再见爱人》第八期高能吐槽！！",
        "tag": "高能,综艺,黄圣依,李行亮,杨子,麦学,再见爱人,麦琳,B站娱乐区综艺解说团,娱乐吃瓜大会8.0"
    },
    {
        "pubdate": "2024-12-07T00:10:00.000Z",
        "arcurl": "https://b23.tv/BV1Y9iZYUE6y",
        "author": "ぬぬぬぬぬぬぬぬぬぬ",
        "title": "ぬぬぬぬぬぬぬぬぬぬぬぬぬぬぬぬぬぬぬぬぬぬぬぬぬぬぬぬぬぬぬぬぬぬぬぬぬぬぬぬぬぬぬぬぬぬぬぬぬぬぬぬぬぬぬぬぬぬぬ￤みむかｩわナイストライ￤初音ミク￤ボカロ",
        "typename": "VOCALOID·UTAU",
        "description": "ぬぬぬぬぬぬぬぬぬぬぬぬぬぬぬぬぬぬぬぬぬぬぬぬぬぬぬぬぬぬぬぬぬぬぬぬぬぬぬぬぬぬぬぬぬぬぬぬぬぬぬぬぬぬぬぬぬぬぬぬぬぬぬぬぬぬぬぬぬぬぬぬぬぬぬぬぬぬぬぬぬぬぬぬぬぬぬぬぬぬぬぬぬぬぬぬぬぬぬぬぬぬぬぬぬぬぬぬぬぬぬぬぬぬぬぬぬぬぬぬぬぬぬぬぬぬぬぬぬぬぬぬぬぬぬぬぬぬぬぬぬぬぬぬぬぬぬぬぬぬぬぬぬぬぬぬぬぬぬぬぬ\n\n【曲名】\n『み　む　かｩ　わ　ナ　イ　ス　ト　ラ　イ』\n\n【曲名】\n「ナイストライ」\n\n【ファンアートタグ・Fan art hashtag】\n『#39neko』\n\n▼曲-絵-動画(Mu",
        "tag": "百万播放"
    },
    {
        "pubdate": "2024-12-06T13:39:57.000Z",
        "arcurl": "http://www.bilibili.com/video/av113606079287714",
        "author": "北斗导航Compass",
        "title": "绝美的新疆独库公路！一天中可观四季【毕业季自驾游第31集】",
        "typename": "出行",
        "description": "",
        "tag": "旅游,在路上,新疆,草原,自驾游,高原,独库公路,那拉提,独库,2024热门年度盘点,冬日出游溜达一下"
    },
    {
        "pubdate": "2024-12-06T11:26:40.000Z",
        "arcurl": "http://www.bilibili.com/video/av113605575973715",
        "author": "糖果果的未来要发光",
        "title": "花2年工资，把房东的房子打造成了我的梦想家｜租房这样改造值得吗？租房Roomtour ~",
        "typename": "日常",
        "description": "啊啊啊啊，room tour终于来了！我太喜欢这个房子了！！\n迫不及待想办粉丝见面会！！！",
        "tag": "改造,房子,装修,家装,家居,生活记录,智能家电,room tour,随手记录我的生活碎片,生活万花筒16.0"
    },
    {
        "pubdate": "2024-12-05T12:42:09.000Z",
        "arcurl": "http://www.bilibili.com/video/av113600257662864",
        "author": "米粒粒儿-",
        "title": "有个会讨价还价的女儿～",
        "typename": "亲子",
        "description": "-",
        "tag": "可爱,情感,女儿,我们的家庭日记,我们的家庭日记11.0"
    },
    {
        "pubdate": "2024-12-05T05:24:23.000Z",
        "arcurl": "http://www.bilibili.com/video/av113598244390852",
        "author": "一只吐槽圆",
        "title": "【2024影视剧奇葩大赏】辣眼演技，迷惑剧情，又是一年共“翔”盛举！",
        "typename": "娱乐杂谈",
        "description": "1.       四十集的写真集——赵露思 《珠帘玉幕》\n2.       豪门千金为逗笑观众使出浑身解数——姚安娜《猎冰》\n3.       世家公子为折磨观众撒币上亿——向佐《门前宝地》\n4.       这二愣子霸总赛道你算是闯出来了——纪凌尘 《恋爱麻烦但是甜》\n5.       我不是来演戏的，我是来看别人演戏的——范丞丞 《小巷人家》\n6.       这就是传说中的正剧咖？——张晚意 《柳舟记》\n7.       太闲了就找个班上吧！——杨紫 张晚意 邓为 檀健次 《长相思2》\n8.    ",
        "tag": "杨紫,自己吓自己,鞠婧祎,向佐,张晚意,赵露思,纪凌尘,范丞丞,姚安娜,2024影娱亿点好活"
    },
    {
        "pubdate": "2024-12-04T12:00:00.000Z",
        "arcurl": "http://www.bilibili.com/video/av113593831988735",
        "author": "动物园会议",
        "title": "糊咖整活出圈、老艺人考古翻车！盘点2024那些没流量却凭“实力”出圈的明星",
        "typename": "娱乐杂谈",
        "description": "",
        "tag": "爆笑,周迅,盘点,名场面,黄磊,韩雪,谷雨,杨子,向佐,2024影娱亿点好活"
    },
    {
        "pubdate": "2024-12-04T09:30:00.000Z",
        "arcurl": "http://www.bilibili.com/video/av113593177676336",
        "author": "刘哔电影",
        "title": "用尽毕生力气只为成为一个普通人！中式现实主义纪录片太敢拍了！",
        "typename": "影视杂谈",
        "description": "",
        "tag": "解说,人物,纪录片,华为,华为影像金鸡手机电影计划,年轻人的奥斯卡"
    },
    {
        "pubdate": "2024-12-03T10:15:00.000Z",
        "arcurl": "http://www.bilibili.com/video/av113587876010849",
        "author": "糖果果的未来要发光",
        "title": "你说的很对，但是你的说话方式让我不舒服……",
        "typename": "日常",
        "description": "步入职场的这一年，我发现沟通技巧真的太重要了！\n很多时候，我经常会跟身边的人讲，你讲的很对，但你的说话方式让人没办法接受。\n大家生活中有遇到消耗式沟通的时候吗？\n\nps：我太喜欢我的这个视频录制背景了，新家room tour这周肯定会发出来～",
        "tag": "交流,心理,情感,人际关系,干货,沟通,内耗,我在B站做公益"
    },
    {
        "pubdate": "2024-12-03T09:20:00.000Z",
        "arcurl": "http://www.bilibili.com/video/av113587641129875",
        "author": "虫哥说电影",
        "title": "黄晓明认真搞笑无厘头古装神片《风流少年唐伯虎》！笑点还是很足的...",
        "typename": "影视杂谈",
        "description": "这应该是黄教主最经典的一部喜剧片吧，笑点还是很足的。",
        "tag": "教主,恶搞,吐槽,搞笑,爆笑,喜剧,黄晓明,何美钿,电影解说,人人都能聊影视,人人都能聊影视4.0"
    },
    {
        "pubdate": "2024-12-03T03:00:00.000Z",
        "arcurl": "http://www.bilibili.com/video/av113584000469156",
        "author": "RICH徐大花",
        "title": "【吃瓜简报】虽然麦学很火热 但其他瓜也不能放过",
        "typename": "娱乐杂谈",
        "description": "",
        "tag": "吐槽,鹿晗,任嘉伦,吃瓜,赵露思,王鹤棣,李庚希,刘宇宁,时代少年团,娱乐吃瓜大会,娱乐吃瓜大会8.0"
    },
    {
        "pubdate": "2024-12-01T11:14:35.000Z",
        "arcurl": "http://www.bilibili.com/video/av113577222478015",
        "author": "岱川博士",
        "title": "岱川博士: 如何读书又快、记忆又深? 干货分享我自用多年的速读技巧",
        "typename": "社科·法律·心理",
        "description": "-",
        "tag": "英语,学习,记忆,读书,看书,经验分享,学习方法,速读,学习心得,新的知识增加了,蓝领2.0"
    },
    {
        "pubdate": "2024-11-30T10:22:35.000Z",
        "arcurl": "http://www.bilibili.com/video/av113571165899035",
        "author": "开心嘴炮",
        "title": "麦琳是回旋镖之王！李行亮却一头钻进麦琳心趴！从未见过如此狂扇观众嘴巴的综艺！《再见爱人》呕血解说",
        "typename": "娱乐杂谈",
        "description": "《再见爱人》第七期高能吐槽！！",
        "tag": "黄圣依,李行亮,杨子,燃气热水器,麦学,再见爱人,麦琳,美的燃气热水器,B站娱乐区综艺解说团,娱乐吃瓜大会8.0,美的无冷感m9smax"
    },
    {
        "pubdate": "2024-11-30T06:24:00.000Z",
        "arcurl": "http://www.bilibili.com/video/av113570327042317",
        "author": "刘哔电影",
        "title": "亮子隶学，完全驯化！",
        "typename": "娱乐杂谈",
        "description": "",
        "tag": "吐槽,搞笑,杜蕾斯,润滑剂,润滑液,杜蕾斯益生元润滑液,B站娱乐区综艺解说团,杜蕾斯玻尿酸润滑液,再见爱人4,李行亮麦琳,娱乐吃瓜大会8.0"
    },
    {
        "pubdate": "2024-11-30T04:27:31.000Z",
        "arcurl": "http://www.bilibili.com/video/av113565747058787",
        "author": "可妈可吗",
        "title": "30万装修180平？装修超绝省钱法！附精确到1块超详细开销表",
        "typename": "家居房产",
        "description": "今天我们来和大家谈谈装修“钱”的事，如何确定装修预算？如何在执行中咬死不要多花钱？全网最真诚装修省钱攻略，作业抄起来！",
        "tag": "家装,#装修避坑,#装修预算,还是淘宝香,#淘宝家电大额补贴,#淘宝以旧换新"
    },
    {
        "pubdate": "2024-11-30T02:05:00.000Z",
        "arcurl": "http://www.bilibili.com/video/av113568682871271",
        "author": "老邪说电影",
        "title": "剧本？补录？世纪炸裂复合，《再见爱人4》请停止侮辱观众智商！",
        "typename": "娱乐杂谈",
        "description": "观众的命难道不是命吗？？",
        "tag": "吐槽,奇葩,李行亮,麦麦,综艺解说,麦琳,娱乐吃瓜大会,再见爱人4,娱乐吃瓜大会8.0"
    },
    {
        "pubdate": "2024-11-29T13:18:56.000Z",
        "arcurl": "http://www.bilibili.com/video/av113566250441046",
        "author": "动物园会议",
        "title": "【吃瓜报告】资源咖、经典唱功、割韭菜新秀！近期内娱吃瓜盘点（11月第3期）",
        "typename": "娱乐杂谈",
        "description": "",
        "tag": "爆笑,五月天,名场面,唱功,唯品会,任嘉伦,费启鸣,范丞丞,资源咖,唯品会128周年庆"
    },
    {
        "pubdate": "2024-11-29T11:30:59.000Z",
        "arcurl": "http://www.bilibili.com/video/av113565964965968",
        "author": "三代鹿人",
        "title": "李行亮麦琳疯狂秀恩爱？我从来没见过这么膈应的剧情！《再见爱人4》放过观众吧！",
        "typename": "娱乐杂谈",
        "description": "尊重！祝福！锁死！\n你们超配超爱超活该！！！",
        "tag": "黄圣依,李行亮,杨子,锁死,再见爱人,麦琳,他超爱,娱乐吃瓜大会,再见爱人4,葛夕,娱乐吃瓜大会8.0"
    },
    {
        "pubdate": "2024-11-29T10:24:11.000Z",
        "arcurl": "http://www.bilibili.com/video/av113565730081254",
        "author": "刘老师说电影",
        "title": "我们都是你们play的一环！《再见爱人》看得我生理性疼痛！",
        "typename": "影视杂谈",
        "description": "没有一个人能毫发无损地走出《再见爱人》。",
        "tag": "搞笑,综艺,黄圣依,李行亮,杨子,留几手,再见爱人,麦琳,人人都能聊影视,人人都能聊影视4.0,葛夕"
    },
    {
        "pubdate": "2024-11-29T09:30:00.000Z",
        "arcurl": "http://www.bilibili.com/video/av113565209986353",
        "author": "话很多的小姐姐们",
        "title": "明年是现偶大年？现代待播剧预告盘点，哪对CP会爆？！",
        "typename": "影视杂谈",
        "description": "今天我们就把待播的现代剧预告都拉出来遛遛，是期待还是抬走？一起来尝尝咸淡！\n本期视频所含电视剧预告有：\n《难哄》白敬亭章若楠\n《许我耀眼》赵露思、陈伟霆\n《嘘！国王在冬眠》虞书欣、林一\n《狙击蝴蝶》陈妍希、周柯宇\n《樱桃琥珀》赵今麦、张凌赫\n《爱你》张凌赫、徐若晗\n《冬至》黄景瑜、孙千\n《白色橄榄树》陈哲远、梁洁\n《哑舍》高伟光、梁靖康\n《异人之下2》彭昱畅、侯明昊、王影璐\n《猎罪图鉴2》檀健次、金世佳\n《钢铁森林》井柏然、蔡文静、秦俊杰\n《三十九，二十八》孙俪、董子健\n《180天重启计划》周雨彤、吴越",
        "tag": "预告,电视剧,哑舍,待播剧,樱桃琥珀,难哄,猎罪图鉴2,异人之下2,嘘！国王在冬眠,许我耀眼"
    },
    {
        "pubdate": "2024-11-29T04:00:00.000Z",
        "arcurl": "http://www.bilibili.com/video/av113563985254747",
        "author": "可妈可吗",
        "title": "谁能想到30岁都带俩娃自驾游了！遛娃圣地浙江安吉vlog",
        "typename": "亲子",
        "description": "感谢极氪7X豪华大五座SUV对本期视频的大力支持，有极氪相伴，家庭出行温馨无憾。",
        "tag": "旅游,杭州,萌娃,自驾游,安吉,带娃,遛娃,二胎家庭,极氪7X,极氪7X还是太全面了"
    },
    {
        "pubdate": "2024-11-27T10:10:00.000Z",
        "arcurl": "http://www.bilibili.com/video/av113553885364797",
        "author": "饲养员小谢",
        "title": "花5W带老公去北极，结果被北极熊困在荒岛上！",
        "typename": "出行",
        "description": "好久不见呀！很抱歉让大家久等了。这期视频是10月和狗哥去北极圈的故事，因为是我特别期待的旅行，狗哥想剪的精彩一些，结果就一直搞到现在了。这也是我们发过的最长的视频。（虽然还是比不了其他出行up）\n\n最近每年我都会给自己一个“去看世界”的小目标，这次选在了北极圈里的斯瓦尔巴群岛，地球上最北的城市。对我来说，北极一直是个既神秘又遥远的地方，斯瓦尔巴算是去北极圈性价比最高的选择了，所以哪怕十月不是个最佳的旅游季，我也还是决定去看看。（因为只有连着国庆才能请这么多天假T T）\n\n由于篇幅的关系其实还有好多想分享的",
        "tag": "生活,搞笑,旅游,北极,情侣,出行,生活记录,vlog,斯瓦尔巴,跟着UP主看世界"
    },
    {
        "pubdate": "2024-11-27T03:00:00.000Z",
        "arcurl": "http://www.bilibili.com/video/av113551083571813",
        "author": "RICH徐大花",
        "title": "是不是只要有情怀就能糊弄观众了《白夜破晓》吐槽",
        "typename": "影视杂谈",
        "description": "",
        "tag": "吐槽,潘粤明,影评杂谈,白夜追凶2,王龙正,白夜破晓,人人都能聊影视,人人都能聊影视4.0"
    },
    {
        "pubdate": "2024-11-25T12:23:04.000Z",
        "arcurl": "http://www.bilibili.com/video/av113543517114379",
        "author": "可妈可吗",
        "title": "什么是好的爱情友情亲情？女导演讽刺“女权表演艺术家”｜《好东西》观后感",
        "typename": "社科·法律·心理",
        "description": "感谢邵艺辉导演的真诚表达与创作，让如此荒凉的电影市场有难得一见的好片！",
        "tag": "爱情,女人,友情,亲情,影评,女权,唠点心理话,《好东西》"
    },
    {
        "pubdate": "2024-11-24T08:58:33.000Z",
        "arcurl": "http://www.bilibili.com/video/av113537057954932",
        "author": "岱川博士",
        "title": "岱川博士: 坐月子、时间匮乏…英国爸爸中国生娃的二三事",
        "typename": "社科·法律·心理",
        "description": "-",
        "tag": "英语,月子,外国人,父母,生育,生孩子,婚姻,跨文化,人生智慧,唠点心理话"
    },
    {
        "pubdate": "2024-11-23T14:23:23.000Z",
        "arcurl": "http://www.bilibili.com/video/av113532695812736",
        "author": "铁铁铁柱_",
        "title": "年度最佳《好东西》，就这个女性视角，爽！",
        "typename": "影视杂谈",
        "description": "非常让人惊喜的是，今年女性题材的影视越来越多了！不是有这么一句话吗？我们现在投的票，就是未来内容市场的样子。所以我不会默默喜欢！我要大声地说出，《好东西》非常好看！非常希望这部电影票房能够越来越好！希望这种女性题材电影越来越多！强烈建议，好东西拍第二部！不拍电影，拍成电视剧也行啊！",
        "tag": "女性,好东西,小叶,宋佳,钟楚曦,王铁梅,邵艺辉,人人都能聊影视,人人都能聊影视4.0"
    },
    {
        "pubdate": "2024-11-21T08:15:59.000Z",
        "arcurl": "",
        "author": "快男Superfast",
        "title": "",
        "typename": "",
        "description": "",
        "tag": ""
    },
    {
        "pubdate": "2024-11-20T14:12:57.000Z",
        "arcurl": "http://www.bilibili.com/video/av113515666937741",
        "author": "高天天天翔",
        "title": "我满心风雪，而你刚好出现",
        "typename": "短片",
        "description": "-",
        "tag": "原创,短片,青春,B站小剧场"
    }
]