[
    {
        "pubdate": "2024-11-23T13:28:16.000",
        "arcurl": "http://www.bilibili.com/video/av113532460931668",
        "author": "北斗导航Compass",
        "title": "驱车1300公里观看黑神话悟空音乐会！",
        "typename": "出行",
        "description": "",
        "tag": "音乐,悟空,现场,交响乐,音乐会,孙悟空,山西,生活记录,黑悟空,黑神话悟空"
    },
    {
        "pubdate": "2024-11-23T13:06:45.000",
        "arcurl": "http://www.bilibili.com/video/av113532393823454",
        "author": "刘哔电影",
        "title": "集麦学大成之作，极致双标，全员亮化！",
        "typename": "娱乐杂谈",
        "description": "做这个节目真的太受气了，跪求关注加一键三连啦~",
        "tag": "吐槽,搞笑,综艺,真人秀,杨子黄圣依,麦学,娱乐吃瓜大会,娱乐吃瓜大会7.0,再见爱人4,李行亮麦琳,留几手葛夕"
    },
    {
        "pubdate": "2024-11-23T10:37:08.000",
        "arcurl": "https://b23.tv/BV1zRByYbEqd",
        "author": "整形医生肖一丁",
        "title": "全国医院活地图｜各地生病去哪看？值得收藏！",
        "typename": "科学科普",
        "description": "-",
        "tag": ""
    },
    {
        "pubdate": "2024-11-23T10:18:03.000",
        "arcurl": "https://b23.tv/BV1iZByYxEop",
        "author": "波士顿圆脸",
        "title": "德媒惊世发言：北溪炸得好，早该炸炸了！",
        "typename": "环球",
        "description": "",
        "tag": "环球·人气飙升"
    },
    {
        "pubdate": "2024-11-23T10:10:14.000",
        "arcurl": "http://www.bilibili.com/video/av113531705888685",
        "author": "托马斯家的",
        "title": "“你们男的为什么都喜欢黑丝啊”",
        "typename": "日常",
        "description": "-",
        "tag": "原创,短片,搞笑,小姐姐,令人心动的crush瞬间,生活万花筒16.0"
    },
    {
        "pubdate": "2024-11-23T09:30:00.000",
        "arcurl": "https://b23.tv/BV1GfUSY4EoQ",
        "author": "兔叭咯",
        "title": "【医学科普】呼噜声大！可能是你的性功能减退了！| 打呼噜需要治吗？",
        "typename": "科学科普",
        "description": "本期视频讲了打呼噜可能导致的危险情况。\n打呼噜是如何威胁生命的？\n教大家几个改善打鼾的小方法~\n希望大家能够认真观看本期视频~\n您可能还喜欢：\n【精神病】BV1T6mfYqEKh\n【异食癖】BV12kDoYMEQR\n【脑额叶手术】BV1VzSoY7EeH\n【尿毒症】BV1xnyDYqEmA\n【膝盖弹响】BV1KtmEYWEMb",
        "tag": "很多人分享"
    },
    {
        "pubdate": "2024-11-23T08:00:00.000",
        "arcurl": "https://b23.tv/BV1QUURYBEkX",
        "author": "哔哩哔哩番剧",
        "title": "英雄联盟：双城之战 第二季 07",
        "typename": "连载动画",
        "description": "#07",
        "tag": ""
    },
    {
        "pubdate": "2024-11-23T06:43:00.000",
        "arcurl": "http://www.bilibili.com/video/av113530883802579",
        "author": "雪西希",
        "title": "踩铃和大胖媳妇又上综艺啦！",
        "typename": "综艺",
        "description": "-",
        "tag": "搞笑,大胖媳妇,张踩铃"
    },
    {
        "pubdate": "2024-11-23T06:09:12.000",
        "arcurl": "https://b23.tv/BV1MVBCYBEbE",
        "author": "电力小子-gtetgeg",
        "title": "《装甲车模拟器》",
        "typename": "极客DIY",
        "description": "我们又与三角洲一拍即合了，大家一起做最优质的战士！（狗头）",
        "tag": "极客DIY·人气飙升"
    },
    {
        "pubdate": "2024-11-23T05:10:50.000",
        "arcurl": "http://www.bilibili.com/video/av113530531480521",
        "author": "快快超爱笑2020",
        "title": "预谋了一场爱的“惊喜揭幕”",
        "typename": "亲子",
        "description": "-",
        "tag": "生日,生活记录,我的养娃日记,我们的家庭日记11.0"
    },
    {
        "pubdate": "2024-11-23T02:05:00.000",
        "arcurl": "http://www.bilibili.com/video/av113529055085070",
        "author": "老邪说电影",
        "title": "裹挟、霸凌、孤立！恐怖如斯！麦麦才是顶级PUA大师！",
        "typename": "综艺",
        "description": "太惨了！",
        "tag": "搞笑,奇葩,李行亮,麦麦,综艺解说,麦琳,B站娱乐区综艺解说团,再见爱人4,葛夕"
    },
    {
        "pubdate": "2024-11-23T02:00:00.000",
        "arcurl": "http://www.bilibili.com/video/av113528165893103",
        "author": "开心嘴炮",
        "title": "拷问麦琳100个问题！我从未见过如此毛骨悚然的发言！《再见爱人》炸裂解说",
        "typename": "娱乐杂谈",
        "description": "《再见爱人》第六期高能吐槽！！",
        "tag": "综艺,李行亮,杨子,追觅,麦学,再见爱人,追觅洗地机,麦琳,B站娱乐区综艺解说团,娱乐吃瓜大会7.0,追觅T40 Ultra洗地机"
    },
    {
        "pubdate": "2024-11-22T16:05:46.000",
        "arcurl": "http://www.bilibili.com/video/av113527343881310",
        "author": "冰蓝色蛋挞",
        "title": "【可妈可吗】直播回放 2024.11.22「再见爱人，你好爱人」",
        "typename": "日常",
        "description": "-",
        "tag": "综艺,情感,情侣,录屏,婚姻,亲密关系,再见爱人,可妈,麦琳,可爸"
    },
    {
        "pubdate": "2024-11-22T14:56:23.000",
        "arcurl": "https://b23.tv/BV1VRBBYNEsn",
        "author": "中气爱",
        "title": "暴雪来了：下半年最大范围寒潮暴雪将至 广东福建不下雪但要猛烈降温",
        "typename": "科学科普",
        "description": "大家都非常关心的大寒潮，形势已经非常清晰，而且已经发生。11月22日晚，寒潮本潮已经来到新疆北部，受强冷空气前锋云系影响，包括乌鲁木齐在内的新疆北部的不少地方已经大雪纷飞，北风怒号，气温快速下降，乌鲁木齐最低温将要下降到-9度左右，最高温也要讲到0度以下。而在此之前，黑龙江也出现了局部降雪。\n当然，和前几年的11月寒潮相比，这种温度并不算极端的低。为什么会这样？正如我们之前节目所说，今年11月西伯利亚暖的实在太厉害，冷空气库存不够，冷源实在不能算强；与此同时，暖湿气流特别强，特别活跃，直到11月下旬，高湿",
        "tag": ""
    },
    {
        "pubdate": "2024-11-22T12:16:04.000",
        "arcurl": "https://b23.tv/BV1k8BiYrEbU",
        "author": "营销号极速版勇闯b站",
        "title": "鉴定网络热门营销号谣言",
        "typename": "科学科普",
        "description": "-",
        "tag": ""
    },
    {
        "pubdate": "2024-11-22T12:14:52.000",
        "arcurl": "http://www.bilibili.com/video/av113526538574502",
        "author": "米粒粒儿-",
        "title": "20后孙女为60后奶奶操碎了心～",
        "typename": "亲子",
        "description": "-",
        "tag": "可爱,女孩,情感,奶奶,女儿,生活记录,我的养娃日记,我们的家庭日记11.0"
    },
    {
        "pubdate": "2024-11-22T12:00:00.000",
        "arcurl": "https://b23.tv/BV1ucBqYpEAG",
        "author": "马鹿blyat",
        "title": "《坦克模拟器4》",
        "typename": "极客DIY",
        "description": "再次感谢《坦克世界》官方，“坦克模拟器4”来啦！还没入坑的兄弟，可通过我的专属链接领取我的专属礼包加入战斗；\n①国服玩家入口：https://urlqh.cn/sUx2s\n②国际服玩家入口：https://tanks.ly/3zXijks 新手邀请码：COMBAT\n同时WCI坦克世界国际冠军赛将于11月23日-24日正式打响！车长们可通过观看WCI直播、完成游戏任务获取点数，领取WCI定制贴花、2D风格、全局经验等精选物品",
        "tag": "百万播放"
    },
    {
        "pubdate": "2024-11-22T11:41:11.000",
        "arcurl": "http://www.bilibili.com/video/av113526387645336",
        "author": "糖果果的未来要发光",
        "title": "博士妈妈死亡教育｜用特效把自己变老，假装穿越未来跟孩子聊死亡……",
        "typename": "亲子",
        "description": "听小十二问出“妈妈，你什么时候死”以后，我差点喷出一口老血。\n但毕竟是亲生的，仔细思考了一下，死亡在我们的童年一直都是讳莫如深的话题。但现在都2024年了，对小朋友进行这方面的教育还是蛮有必要的。\n于是用上了科技，让72岁的我给小十二打了一通电话……\n你是怎么看待这个问题的呢？会觉得这样对待小孩子有些残忍吗？",
        "tag": "母子,小朋友,情感,父母,整蛊,高甜,亲子教育,死亡教育,变老特效,我的养娃日记,我们的家庭日记11.0"
    },
    {
        "pubdate": "2024-11-22T11:07:30.000",
        "arcurl": "http://www.bilibili.com/video/av113526270073861",
        "author": "三代鹿人",
        "title": "救命啊！麦琳究极折磨所有人！《再见爱人4》看得我想死了！！！",
        "typename": "娱乐杂谈",
        "description": "你以为熏鸡事变是她的巅峰？\n不！这只是麦姐表演的开始！",
        "tag": "折磨,黄圣依,李行亮,杨子,工伤,再见爱人,麦琳,娱乐吃瓜大会,娱乐吃瓜大会7.0,再见爱人4,葛夕"
    },
    {
        "pubdate": "2024-11-22T10:40:00.000",
        "arcurl": "https://b23.tv/BV1pSUdYoEEv",
        "author": "吃不完的赛罗酱",
        "title": "【4K 奥特无缝衔接】震撼大赏！纵享丝滑到飞起的视觉盛宴！！",
        "typename": "特摄",
        "description": "之前答应的上上上个视频的完整版，我没鸽！！！",
        "tag": "百万播放"
    },
    {
        "pubdate": "2024-11-22T10:30:30.000",
        "arcurl": "https://b23.tv/BV1yTBqY7Eyf",
        "author": "波士顿圆脸",
        "title": "反川阻击大成功：折戟参议院司法部长换将最速传说",
        "typename": "环球",
        "description": "",
        "tag": ""
    },
    {
        "pubdate": "2024-11-22T10:23:14.000",
        "arcurl": "http://www.bilibili.com/video/av113526085586888",
        "author": "low君热剧",
        "title": "高开疯走！一期比一期精彩！他们疯了，但我看开了！《再见爱人4》",
        "typename": "娱乐杂谈",
        "description": "",
        "tag": "黄圣依,李行亮,杨子,麦麦,留几手,刘爽,麦琳,再见爱人4,葛夕,爆改恋综"
    },
    {
        "pubdate": "2024-11-22T10:00:00.000",
        "arcurl": "https://b23.tv/BV1qDUPYKEzf",
        "author": "DECO27_Official",
        "title": "DECO*27 - モニタリング feat. 初音ミク",
        "typename": "VOCALOID·UTAU",
        "description": "「ねえあたし知ってるよ」\n\n2024年11月27日発売\n9th Album 「TRANSFORM」 特設サイト\nhttps://nbcuni-music.com/deco27\n\nLyrics & Music: DECO*27\nArrangement: DECO*27 & Hayato Yamamoto\n\nMovie by OTOIRO\nDirector: kee\nCharacter Designer: kee\nKey Animator: kee, 1024\nAnimator: 白木メラ, なくり, 橙瀬あ",
        "tag": "6万点赞"
    },
    {
        "pubdate": "2024-11-22T09:51:39.000",
        "arcurl": "http://www.bilibili.com/video/av113525968142796",
        "author": "小片片说大片",
        "title": "假死，诈尸，替身查案，终于等来这部国产神剧的填坑续集！国产刑侦剧《白夜破晓》第一案",
        "typename": "影视杂谈",
        "description": "提到国产高分刑侦剧，你一定会想到它：《白夜追凶》。\n7年后的今天，它的续集《白夜破晓》，终于上线了！",
        "tag": "推理,悬疑,犯罪,潘粤明,刑侦,探案,梁缘,王龙正,白夜破晓,白夜追凶2有生之年系列"
    },
    {
        "pubdate": "2024-11-22T09:30:00.000",
        "arcurl": "https://b23.tv/BV1rfUUYqEd8",
        "author": "HOPICO",
        "title": "3秒后你会开始\"落泪\"?华语前奏排行榜（二）丨HOPICO",
        "typename": "电台",
        "description": "喜欢的话，请记得三连支持呀！\n祝你冬天快乐！",
        "tag": ""
    },
    {
        "pubdate": "2024-11-22T02:30:00.000",
        "arcurl": "https://b23.tv/BV1PFU9YWEzY",
        "author": "星球研究所",
        "title": "什么？！中国的土地一直在增长？【4K】",
        "typename": "科学科普",
        "description": "欢迎观看由 宝马集团 × 星球研究所 联合创作的视频，一起探索年轻土地诞生的奥秘，成为#美丽家园守护者#。",
        "tag": "5万点赞"
    },
    {
        "pubdate": "2024-11-21T14:50:56.000",
        "arcurl": "http://www.bilibili.com/video/av113521488626282",
        "author": "快快超爱笑2020",
        "title": "她也到会读信的年龄了",
        "typename": "亲子",
        "description": "-",
        "tag": "小朋友,萌娃,生活记录"
    },
    {
        "pubdate": "2024-11-21T13:21:47.000",
        "arcurl": "http://www.bilibili.com/video/av113521119462467",
        "author": "刘老师说电影",
        "title": "时隔7年，《白夜追凶》续集突袭上线，《白夜破晓》你很勇嘛！",
        "typename": "影视杂谈",
        "description": "期待下一桩儿童拐卖案",
        "tag": "悬疑,犯罪,潘粤明,刑侦,白夜追凶,新剧好剧一起看,白夜破晓,人人都能聊影视4.0"
    },
    {
        "pubdate": "2024-11-21T11:03:16.000",
        "arcurl": "http://www.bilibili.com/video/av113520599374934",
        "author": "米粒粒儿-",
        "title": "爸爸跟她斗嘴，这局是不是输了～",
        "typename": "亲子",
        "description": "-",
        "tag": "可爱,爸爸,亲子,萌娃,生活记录,我的养娃日记,我们的家庭日记11.0"
    },
    {
        "pubdate": "2024-11-21T09:45:00.000",
        "arcurl": "https://b23.tv/BV1gkUUYJEHG",
        "author": "赛博食录",
        "title": "【食录】为什么韩国人如此热衷于喝冰美式？",
        "typename": "科学科普",
        "description": "如果遇上裹着黑色长款羽绒服、手指冻得通，红却依旧倔强地拿着杯冰美式在那哆哆嗦嗦的人，那么他将被初步诊断为韩国人。",
        "tag": "百万播放"
    },
    {
        "pubdate": "2024-11-21T08:15:59.000",
        "arcurl": "",
        "author": "快男Superfast",
        "title": "",
        "typename": "",
        "description": "",
        "tag": ""
    },
    {
        "pubdate": "2024-11-20T14:12:57.000",
        "arcurl": "http://www.bilibili.com/video/av113515666937741",
        "author": "高天天天翔",
        "title": "我满心风雪，而你刚好出现",
        "typename": "短片",
        "description": "-",
        "tag": "原创,短片,青春,B站小剧场"
    },
    {
        "pubdate": "2024-11-20T12:54:01.000",
        "arcurl": "https://b23.tv/BV1jKSgYWE8h",
        "author": "盐边张家川北林",
        "title": "蔚蓝催眠术",
        "typename": "音MAD",
        "description": "sm44341743 / https://youtu.be/gsCduEfQhio\n作者: SakiZ\n\nBGM: サツキ - メズマライザー(BV15J4m1A7qy)",
        "tag": ""
    },
    {
        "pubdate": "2024-11-20T10:56:31.000",
        "arcurl": "http://www.bilibili.com/video/av113514911897909",
        "author": "可妈可吗",
        "title": "真羡慕娃！才三岁就看过歼-20了！航展vlog",
        "typename": "亲子",
        "description": "现在的孩子如果做军事迷的话，应该是件很幸福的事情吧！",
        "tag": "飞机,军事,珠海,歼20,航展,生活记录,苏57,2024珠海航展,第十五届中国航展"
    },
    {
        "pubdate": "2024-11-20T10:02:09.000",
        "arcurl": "http://www.bilibili.com/video/av113514307983252",
        "author": "糖果果的未来要发光",
        "title": "针对不同岗位精准提问！有Ai面试官还怕拿不到offer？",
        "typename": "职业职场",
        "description": "最近我的一个硕士学弟面试屡屡受挫，跟我聊天的时候，我和学长突发奇想，可以给受面试困扰的人开发一款AI面试的工具。之前也看到有新闻说硅谷有创业者通过设计AI面试官，获得了上千万的融资。\n\n感觉AI面试官的需求的确很大，我和学长说干就干，设计了一个AI面试官，大家帮我们试试看，好不好用。而且大家还可以根据我视频的步骤，自己去调整测试，生成每个人个性化的面试官，比如考研面试官，考公面试官。\n\n如果大家有好的点子，也欢迎大家在评论区跟我们分享。",
        "tag": "互联网,面试,人工智能,AI,求职,扣子,面试技巧,秋招,Coze,技术人儿来报道,技术人儿来报道！"
    },
    {
        "pubdate": "2024-11-20T09:30:00.000",
        "arcurl": "http://www.bilibili.com/video/av113514073036616",
        "author": "虫哥说电影",
        "title": "湖南卫视自制商战偶像剧《童话二分之一》！张钧甯分裂两个千金...",
        "typename": "影视杂谈",
        "description": "他们四个人，到底谁更爱谁？",
        "tag": "吐槽,童年,搞笑,何炅,张翰,朱梓骁,张钧甯,蔡徐坤,电视剧解说,人人都能聊影视,人人都能聊影视4.0"
    },
    {
        "pubdate": "2024-11-19T11:44:27.000",
        "arcurl": "https://b23.tv/BV1tsUfYrEFG",
        "author": "子非秋月",
        "title": "张载：我用58年做了一个梦，一个万世太平的梦",
        "typename": "电台",
        "description": "横渠四句，震古烁今，但又谁真正了解这四句话背后的故事，和他的人生呢，本期视频，希望给你不一样的内容跟感悟。他的名字，叫做张载，58年，如同一个梦。半生风雨，多少未竟之事，多少未尽之言，此刻似乎都归于了宁静。他收起笔，将最后的文稿轻轻压在书卷下，然后站起身，走到窗前。他望向远方，月光下的群山沉默无言，却仿佛在静静聆听。他伸手触碰窗棂，指尖有些冰凉，微微颤动，但他的眼神依旧笃定，像一盏永不熄灭的灯。风停了，月光洒满整个房间。什么都没有发生，什么都已经发生。 ——张载篇\n\n视频内容参考：\n\n《宋史·卷四百二十七",
        "tag": ""
    },
    {
        "pubdate": "2024-11-19T11:11:53.000",
        "arcurl": "http://www.bilibili.com/video/av113509274881759",
        "author": "开心嘴炮",
        "title": "彻底戳穿麦琳惯用话术！逼得杨子后悔上节目，黄圣依劝得腿都麻了！全员反思何时休",
        "typename": "娱乐杂谈",
        "description": "《再见爱人》第五期加更深度解说",
        "tag": "爆笑,高能,综艺,黄圣依,李行亮,杨子,麦学,再见爱人,麦琳,B站娱乐区综艺解说团,娱乐吃瓜大会7.0"
    },
    {
        "pubdate": "2024-11-18T12:36:51.000",
        "arcurl": "http://www.bilibili.com/video/av113503956373446",
        "author": "可妈可吗",
        "title": "怎么有人吃面这么可爱啊…",
        "typename": "日常",
        "description": "怎么有人吃面这么可爱啊…",
        "tag": "小视频"
    },
    {
        "pubdate": "2024-11-18T11:26:49.000",
        "arcurl": "http://www.bilibili.com/video/av113503587276578",
        "author": "Claire的编辑室",
        "title": "麦琳李行亮真的相爱吗？杨子成功洗白？再见爱人4深度解析！",
        "typename": "影视杂谈",
        "description": "最近《再见爱人4》热播，谁也没想到，这一档已经播出了三季的离婚综艺，看似已经把婚姻中的鸡零狗碎、纠结纷争，统统拍透了，没想到竟然在第四季，还焕发出新的生命活力。\n\t\n\t大家好，这里是Claire的编辑室，我是做影视与文化解析的Claire。\n\t  \n\t本期视频，让我们走近《再见爱人4》，来分别聊聊李行亮和麦琳、黄圣依和杨子这两对。无论他们之间是表演、打配合、还是觉醒后的起身对抗，都将成为综艺史上浓墨重彩的一笔。",
        "tag": "娱乐,女性,综艺,黄圣依,李行亮,杨子,深度解析,麦琳,人人都能聊影视,人人都能聊影视4.0,再见爱人4"
    },
    {
        "pubdate": "2024-11-18T10:00:00.000",
        "arcurl": "http://www.bilibili.com/video/av113502345758133",
        "author": "小片片说大片",
        "title": "65万人打出9.1的高分！一口气速通最强国产刑侦剧《白夜追凶》！",
        "typename": "影视杂谈",
        "description": "一人四角，狂飙演技，刑侦白月光回归！\n苦等七年！第二季终于来了！",
        "tag": "高分,犯罪,潘粤明,刑侦,探案,白夜追凶,王龙正,白夜破晓,人人都能聊影视,人人都能聊影视4.0"
    },
    {
        "pubdate": "2024-11-18T04:08:10.000",
        "arcurl": "https://b23.tv/BV1xzUJYZEbh",
        "author": "吴允博-球球",
        "title": "一个人随性trouble maker…",
        "typename": "街舞",
        "description": "-",
        "tag": "百万播放"
    },
    {
        "pubdate": "2024-11-17T09:52:13.000",
        "arcurl": "https://b23.tv/BV1FMU6Y6Euz",
        "author": "怀旧音悦台",
        "title": "怪不得大家总说音乐不分国界！原来即便我们听不懂歌词仅凭旋律也能让人一秒上头！",
        "typename": "乐评盘点",
        "description": "",
        "tag": ""
    },
    {
        "pubdate": "2024-11-17T09:12:12.000",
        "arcurl": "http://www.bilibili.com/video/av113497497146803",
        "author": "岱川博士",
        "title": "岱川博士: 为何你总是无法提升自己的「认知高度」?",
        "typename": "社科·法律·心理",
        "description": "-",
        "tag": "英语,学习,读书,心理学,博士,信息,认知,人生智慧,认知高度,社会观察局,请回答这个时代5.0"
    },
    {
        "pubdate": "2024-11-17T05:25:49.000",
        "arcurl": "http://www.bilibili.com/video/av113496608020210",
        "author": "三代鹿人",
        "title": "它上映前被狂打低分，上映后却好评如潮！这部电影为何如此两极分化？",
        "typename": "影视杂谈",
        "description": "看之前没想到会是这种电影…\n-\n好东西",
        "tag": "好东西,国产电影,国产片,单亲妈妈,宋佳,钟楚曦,邵艺辉"
    },
    {
        "pubdate": "2024-11-17T02:00:00.000",
        "arcurl": "http://www.bilibili.com/video/av113461845630727",
        "author": "硬核妈妈丽洁",
        "title": "这次真是大制作了宝儿们！",
        "typename": "搞笑",
        "description": "这次真是大制作了宝儿们！",
        "tag": "恶搞,搞笑,教育,宿舍,亲子,生活记录,林呱呱,原创搞笑剧情,韩美美,#BILIBILI金电视奖#,BILIBILI金电视奖2.0"
    },
    {
        "pubdate": "2024-11-16T13:37:45.000",
        "arcurl": "http://www.bilibili.com/video/av113492849857773",
        "author": "刘哔电影",
        "title": "麦琳完全体一出，留几手道歉，杨子崩溃，全员反思！",
        "typename": "娱乐杂谈",
        "description": "",
        "tag": "吐槽,搞笑,娱乐,综艺,真人秀,黄圣依杨子,娱乐吃瓜大会,娱乐吃瓜大会7.0,再见爱人4,李行亮麦琳,留几手葛夕"
    },
    {
        "pubdate": "2024-11-16T10:05:42.000",
        "arcurl": "http://www.bilibili.com/video/av113492027839704",
        "author": "北斗导航Compass",
        "title": "【帅谈】时隔一年多再次与台湾小哥Jim爆笑访谈（上集）",
        "typename": "科学科普",
        "description": "",
        "tag": "音乐,UP主,新闻,访谈,台湾,采访,综艺,研究生,杂谈,读博"
    },
    {
        "pubdate": "2024-11-16T08:11:46.000",
        "arcurl": "http://www.bilibili.com/video/av113491608342364",
        "author": "一只吐槽圆",
        "title": "内娱综艺紫薇星麦琳登基！集集都炸裂，秒秒有槽点【再见爱人4】",
        "typename": "娱乐杂谈",
        "description": "",
        "tag": "黄圣依,李行亮,杨子,黄执中,留几手,papi酱,再见爱人,麦琳,B站娱乐区综艺解说团,娱乐吃瓜大会7.0,葛夕"
    },
    {
        "pubdate": "2024-11-16T03:18:00.000",
        "arcurl": "http://www.bilibili.com/video/av113488873653375",
        "author": "RICH徐大花",
        "title": "古偶打架again  毫无争议的烂剧PK有点争议的好剧",
        "typename": "影视杂谈",
        "description": "实用新型专利证书\n实用新型名称 ：一种多功能枕头\n专 利 号：ZL 2022 2 2654375.2\n\n外观设计专利证书\n外 观 设 计 名 称：枕头（云梦枕Z3）\n专 利 号：ZL 2022 3 0664459.7",
        "tag": "吐槽,陈都灵,侯明昊,赵露思,虞书欣,古偶,刘宇宁,珠帘玉幕,永夜星河,大梦归离"
    },
    {
        "pubdate": "2024-11-16T03:00:00.000",
        "arcurl": "http://www.bilibili.com/video/av113486139102327",
        "author": "高天天天翔",
        "title": "你总是用放大镜看自己配不配，却总忽略自己想不想",
        "typename": "短片",
        "description": "-",
        "tag": "剧情,情感,原生家庭,配得感,得物"
    },
    {
        "pubdate": "2024-11-16T02:10:30.000",
        "arcurl": "http://www.bilibili.com/video/av113490182411423",
        "author": "三代鹿人",
        "title": "又哭又闹极度双标，麦姐离婚孩子和钱全都要？《再见爱人》最新一期太毁三观了！",
        "typename": "娱乐杂谈",
        "description": "看完这周更生气了！！！\n-\n求个点赞三连，我们一起看看这节目下期还能怎么作？",
        "tag": "黄圣依,李行亮,杨子,留几手,麦学,再见爱人,麦琳,娱乐吃瓜大会,娱乐吃瓜大会7.0,再见爱人4,葛夕"
    },
    {
        "pubdate": "2024-11-16T02:00:00.000",
        "arcurl": "http://www.bilibili.com/video/av113487581939346",
        "author": "开心嘴炮",
        "title": "麦琳闹离婚名场面！麦学逼疯所有人！全世界都要围着她转？！《再见爱人》高能解说",
        "typename": "娱乐杂谈",
        "description": "听说麦琳选离婚啦？！\n高能解说《再见爱人》第五期",
        "tag": "爆笑,高能,综艺,黄圣依,李行亮,杨子,麦学,再见爱人,麦琳,B站娱乐区综艺解说团,娱乐吃瓜大会7.0"
    },
    {
        "pubdate": "2024-11-16T02:00:00.000",
        "arcurl": "http://www.bilibili.com/video/av113487212709853",
        "author": "low君热剧",
        "title": "傻白甜不该是个贬义词，傻白甜也能拥有强大内核！",
        "typename": "影视杂谈",
        "description": "已经十年了",
        "tag": "张翰,赵丽颖,傻白甜,杉杉来了,薛杉杉,封腾,人人都能聊影视,饿了么17吃货节,人人都能聊影视4.0,1117饿了么免单升级全年免单"
    },
    {
        "pubdate": "2024-11-15T12:57:42.000",
        "arcurl": "http://www.bilibili.com/video/av113486894008318",
        "author": "话很多的小姐姐们",
        "title": "11月古偶试毒：95花打起来了！郭敬明关的门！",
        "typename": "影视杂谈",
        "description": "最新播出的古偶到底都怎么样呢？快来跟我们一起看看吧",
        "tag": "郭敬明,陈都灵,侯明昊,虞书欣,古偶,丁禹兮,永夜星河,大梦归离,饿了么17吃货节,1117饿了么免单升级全年免单"
    },
    {
        "pubdate": "2024-11-15T09:49:08.000",
        "arcurl": "http://www.bilibili.com/video/av113486206146171",
        "author": "虫哥说电影",
        "title": "早年情感综艺奇葩合集！把他们全送去再见爱人~",
        "typename": "娱乐杂谈",
        "description": "这些高能嘉宾，他们到底是剧本还是真实的啊~",
        "tag": "吐槽,搞笑,爆笑,恋爱,高能,相亲,黄圣依,李金铭,自信姐,B站娱乐区综艺解说团,娱乐吃瓜大会7.0"
    },
    {
        "pubdate": "2024-11-15T05:04:48.000",
        "arcurl": "http://www.bilibili.com/video/av113485199513229",
        "author": "北斗导航Compass",
        "title": "这是全网第一条测评马督工团队伙食的视频——拜访马督工团队",
        "typename": "出行",
        "description": "",
        "tag": "UP主,创作,美食,记录,测评,生活记录,视频拍摄,马前卒,马督工,键政"
    },
    {
        "pubdate": "2024-11-15T04:05:00.000",
        "arcurl": "http://www.bilibili.com/video/av113484008260523",
        "author": "老邪说电影",
        "title": "邋遢乱扔纸、背刺好闺蜜，详扒麦麦离奇操作，堪称六边形极致折磨战士！",
        "typename": "娱乐杂谈",
        "description": "原来熏鸡事件也仅仅只是冰山一角！",
        "tag": "搞笑,真人秀,影视剪辑,李行亮,麦麦,留几手,离谱,再见爱人,B站娱乐区综艺解说团,娱乐吃瓜大会7.0,葛夕"
    },
    {
        "pubdate": "2024-11-14T10:00:00.000",
        "arcurl": "http://www.bilibili.com/video/av113480065621937",
        "author": "糖果果的未来要发光",
        "title": "揭秘5个潜力巨大的新兴职业！",
        "typename": "职业职场",
        "description": "最近又到了秋招季，不知道大家今年的就业情况怎么样。最近跟好几个正在找工作的学弟和学妹们聊了聊，发现有很多我之前都没听过的职业出现，跟大家分享了5个现在的新型职业，大家感兴趣的话，可以多去了解呀。",
        "tag": "互联网,职业,大学生,职场,潜力,就业,3M,秋招,新兴职业,今天也要好好工作,技术人儿来报道！"
    },
    {
        "pubdate": "2024-11-13T14:15:26.000",
        "arcurl": "http://www.bilibili.com/video/av113476055859738",
        "author": "快快超爱笑2020",
        "title": "在陪伴这门功课上妈妈不及格",
        "typename": "亲子",
        "description": "-",
        "tag": "妈妈,生活记录,我的养娃日记,我们的家庭日记11.0"
    },
    {
        "pubdate": "2024-11-12T10:35:04.000",
        "arcurl": "http://www.bilibili.com/video/av113469529525760",
        "author": "小片片说大片",
        "title": "年度好片！这题材，能拍出来，能上映，就赢了！真实事件改编《白日之下》",
        "typename": "影视杂谈",
        "description": "《白日之下》上映后，在第42届香港金像奖荣获16项提名。\n影片以极其写实的手法，揭露了香港各类院舍的黑暗现状。\n其中百分之八十的虐待情节，都取材自香港养老院与残疾院的真实事件！\n电影黑暗程度堪比《熔炉》，一度颠覆观众认知。",
        "tag": "人性,犯罪,真实事件改编,林保怡,姜大卫,余香凝,白日之下,人人都能聊影视,人人都能聊影视4.0"
    },
    {
        "pubdate": "2024-11-11T09:20:00.000",
        "arcurl": "http://www.bilibili.com/video/av113463087141211",
        "author": "虫哥说电影",
        "title": "外星姐妹入侵地球？卫斯理的竟然是个复制体！《少年王》的脑洞继续增大~",
        "typename": "影视杂谈",
        "description": "《少年王》这个单元的外星姐妹大小乔真的让人印象深刻~~",
        "tag": "经典,童年,搞笑,科幻,回忆杀,吴奇隆,周易,少年王,电视剧解说,人人都能聊影视,人人都能聊影视4.0"
    },
    {
        "pubdate": "2024-11-10T12:29:27.000",
        "arcurl": "http://www.bilibili.com/video/av113458624336521",
        "author": "刘哔电影",
        "title": "表演型在天赋面前不值一提，麦姐两只熏鸡干碎杨子叶柯热搜梦！",
        "typename": "娱乐杂谈",
        "description": "",
        "tag": "吐槽,搞笑,综艺,李行亮,留几手,黄圣依杨子,麦琳,娱乐吃瓜大会,娱乐吃瓜大会7.0,再见爱人4,葛夕"
    },
    {
        "pubdate": "2024-11-10T02:48:40.000",
        "arcurl": "http://www.bilibili.com/video/av113456359412298",
        "author": "三代鹿人",
        "title": "怎么会有这么恶心的人？！全方位吐槽气炸全网的《再见爱人4》！",
        "typename": "娱乐杂谈",
        "description": "你懂吗？你造吗？看完这个节目我整个人gin住，完全气在了我的心趴上！\n-\n求个点赞三连，我们一起看看这节目下期还能怎么作？",
        "tag": "黄圣依,李行亮,杨子,留几手,熏鸡,麦学,再见爱人,麦琳,娱乐吃瓜大会,娱乐吃瓜大会7.0,再见爱人4"
    },
    {
        "pubdate": "2024-11-10T02:00:00.000",
        "arcurl": "http://www.bilibili.com/video/av113454077708701",
        "author": "开心嘴炮",
        "title": "熏鸡事变！麦学终极奥义！吃完狂笑不止！《再见爱人》高能解说",
        "typename": "娱乐杂谈",
        "description": "《再见爱人》是怎么做到的\n一期更比一期气人的？？\n《再见爱人》解说第四期",
        "tag": "爆笑,黄圣依,李行亮,杨子,张泉灵,熏鸡,麦学,再见爱人,麦琳,B站娱乐区综艺解说团,娱乐吃瓜大会7.0"
    },
    {
        "pubdate": "2024-11-09T11:11:51.000",
        "arcurl": "http://www.bilibili.com/video/av113452567756864",
        "author": "刘老师说电影",
        "title": "揭露真实存在的韩国邪教，性侵虐待，无恶不作！解说纪录片《以神之名：信仰的背叛》",
        "typename": "影视杂谈",
        "description": "纪录片第一部分，揭露的是“摄理教”JMS创始人郑明析。",
        "tag": "韩国,纪录片,社会,韩国电影,人人都能聊影视,人人都能聊影视4.0"
    },
    {
        "pubdate": "2024-11-09T11:11:38.000",
        "arcurl": "http://www.bilibili.com/video/av113452316168030",
        "author": "一只吐槽圆",
        "title": "芒果台养蛊呢？娱乐圈开启NPD大乱斗时代！【麦琳｜周雨彤｜杨子】",
        "typename": "娱乐杂谈",
        "description": "",
        "tag": "陈好,黄圣依,李行亮,杨子,花儿与少年,金晨,周雨彤,再见爱人,麦琳,还是淘宝香"
    },
    {
        "pubdate": "2024-11-09T09:41:20.000",
        "arcurl": "http://www.bilibili.com/video/av113452248997854",
        "author": "铁铁铁柱_",
        "title": "终于来了一对好磕的BG！虞书欣丁禹兮赵一龙救我狗命！《永夜星河》",
        "typename": "影视杂谈",
        "description": "栩栩！这里甜宠酵母我要跟你推心置腹说几句了\n之后的剧情你不要作妖！\n要想之后还能拥有现在的笑容！\n学习于正这个死叉叉，看到苗头不对，该删删！该改改！或者拍个番外什么的？这波红利还是你吃！",
        "tag": "爱情,电视剧,安利,赵一龙,虞书欣,丁禹兮,永夜星河,人人都能聊影视,人人都能聊影视4.0"
    },
    {
        "pubdate": "2024-11-09T04:05:00.000",
        "arcurl": "http://www.bilibili.com/video/av113448977436026",
        "author": "老邪说电影",
        "title": "一己之力喜提全网痛骂！太逆天！麦麦求你放过大家吧！",
        "typename": "娱乐杂谈",
        "description": "麦麦开始发力，杨子看起来都顺眼多了！",
        "tag": "吐槽,奇葩,黄圣依,李行亮,杨子,麦麦,综艺解说,麦琳,B站娱乐区综艺解说团,娱乐吃瓜大会7.0,再见爱人4"
    },
    {
        "pubdate": "2024-11-09T03:00:00.000",
        "arcurl": "http://www.bilibili.com/video/av113446947455089",
        "author": "话很多的小姐姐们",
        "title": "《小巷人家》：不憋屈的年代剧，中女给我狠狠上桌！",
        "typename": "影视杂谈",
        "description": "谁敢想啊，佟掌柜和华妃娘娘居然在一部剧里当起了闺蜜！",
        "tag": "好剧,闫妮,蒋欣,年代剧,李光洁,影视杂谈,郭晓东,张开宙,小巷人家"
    },
    {
        "pubdate": "2024-11-07T10:00:00.000",
        "arcurl": "http://www.bilibili.com/video/av113440370794021",
        "author": "铁铁铁柱_",
        "title": "太好了，是郭敬明，《大梦归离》没救了！【铁柱】",
        "typename": "影视杂谈",
        "description": "整个故事，也是小四本人给我的感觉——\n他喜欢写青春的故事，45度角仰望天空的明媚忧伤\n从主角到单元剧故事，都是同一个逻辑\n虽然我杀了很多人，但是我是有苦衷的\n他喜欢塑造一些犯下大错的角色\n不是说不愿意让你塑造有缺点的角色\n而是这货的叙事比例严重失衡\n习惯性美化加害者 忽略受害人\n高高拿起，轻轻放下\n内核经不起推敲\n它笔下的角色，就跟他一样\n一个活在自己世界永远长不大的，不愿意承担责任的巨婴",
        "tag": "吐槽,郭敬明,人人都能聊影视,大梦归离,人人都能聊影视4.0"
    },
    {
        "pubdate": "2024-11-06T11:00:00.000",
        "arcurl": "http://www.bilibili.com/video/av113434867801603",
        "author": "动物园会议",
        "title": "【吃瓜报告】虞书欣赵露思新剧对打、周雨彤道歉、窒息麦学！近期热门瓜盘点（11月第1期）",
        "typename": "娱乐杂谈",
        "description": "请仔细阅读产品说明书或在医务人员的指导下购买和使用",
        "tag": "周雨彤,花少,侯明昊,赵露思,虞书欣,古偶,95花,再见爱人,麦琳"
    },
    {
        "pubdate": "2024-11-06T10:12:48.000",
        "arcurl": "http://www.bilibili.com/video/av113435455066192",
        "author": "糖果果的未来要发光",
        "title": "原来两大车就能搬走我的幸福...",
        "typename": "日常",
        "description": "啊啊啊，终于搬家了，很久之前看到一个数据，大约是说每个中国人，平均下来一生中会搬9次家，才会最终稳定下来，虽然搬家很累，但想一想，也许搬着搬着就有了自己的家，也感觉到很幸福。\n\n后面我们会有超级好看的room tour，但是可能大家要等一等了，因为房子我们做了很大的改动。但绝对好看，大家可以提前预约一波～",
        "tag": "人工智能,搬家,装修,家装,家居,房屋改造,生活记录,智能家电,数码测评,随手记录我的生活碎片,生活万花筒15.0—给生活的秋日来信"
    },
    {
        "pubdate": "2024-11-06T09:50:00.000",
        "arcurl": "http://www.bilibili.com/video/av113429717190087",
        "author": "张踩铃",
        "title": "张拿铁拒绝说中文",
        "typename": "日常",
        "description": "",
        "tag": "搞笑,一定要看到最后,文化差异"
    },
    {
        "pubdate": "2024-11-06T09:20:00.000",
        "arcurl": "http://www.bilibili.com/video/av113434414878810",
        "author": "虫哥说电影",
        "title": "邪恶版王宝钏有仇必报！超直接的宫廷神剧《万凰之王》，这一次绝不吃野菜！",
        "typename": "影视杂谈",
        "description": "这是我看过最嚣张的妃子，连太后也一起噶了！！\n这部剧是和王宝钏同一时期拍的，两个角色完全不一样~",
        "tag": "吐槽,搞笑,胡定欣,宣萱,胡杏儿,清宫剧,电影解说,影评杂谈,电视剧解说,人人都能聊影视,人人都能聊影视4.0"
    },
    {
        "pubdate": "2024-11-05T11:32:46.000",
        "arcurl": "http://www.bilibili.com/video/av113430103069031",
        "author": "铁铁铁柱_",
        "title": "年度黑马！电子榨菜！来看闫妮蒋欣的绝美闺蜜情！《小巷人家》【铁柱】",
        "typename": "影视杂谈",
        "description": "一款振兴客厅文化的神奇电视剧，是你和你妈你爸你爷你奶都能看的电视剧！统一了全家的审美！",
        "tag": "电视剧,黑马,好剧,闫妮,闺蜜,蒋欣,小巷人家,人人都能聊影视,人人都能聊影视4.0"
    },
    {
        "pubdate": "2024-11-05T11:00:00.000",
        "arcurl": "http://www.bilibili.com/video/av113428828000567",
        "author": "Claire的编辑室",
        "title": "电影大批斗？观众饭圈化？到底是什么真正毁掉国产电影？",
        "typename": "影视杂谈",
        "description": "截至目前，纵观2024年所有上映的国产电影，从春节档、五一档、再到刚结束的国庆档，我们能发现，无论是国产商业大片、文艺片、现实主义题材、还是喜剧片，都没有出现一部，口碑、票房实现双丰收的国民爆款。\n\t\n\t从《封神》导演乌尔善执导的新片、胡乱改编原著、无处不在的恶趣味、性暗示、暴露镜头的《异人之下》；\n\t再到烂到让人忍不住边看边气笑的、陆川哭诉自己花费八年时间精心打磨的、实则却是和《上海堡垒》手拉手并排站的大烂片《749局》；\n\t再到丁晟执导，杨幂、于谦主演，不得不提前撤档、剧情比短视频还要稀烂、强行反转、",
        "tag": "喜剧,电影,杨幂,王俊凯,国产片,赵丽颖,影评杂谈,749局,流浪地球2,弹嫩源来易如反掌"
    },
    {
        "pubdate": "2024-11-04T12:27:29.000",
        "arcurl": "http://www.bilibili.com/video/av113424633765489",
        "author": "刘哔电影",
        "title": "“谁说这麦麦不行啊，这麦麦太好了！”",
        "typename": "娱乐杂谈",
        "description": "",
        "tag": "吐槽,搞笑,解说,综艺,婚姻,李行亮,麦琳,娱乐吃瓜大会,娱乐吃瓜大会7.0,再见爱人4"
    },
    {
        "pubdate": "2024-11-04T03:15:00.000",
        "arcurl": "http://www.bilibili.com/video/av113422318437205",
        "author": "RICH徐大花",
        "title": "【吃瓜简报】花磊珂学 怎么学都很强  两个电影 不知所云还挺忙",
        "typename": "娱乐杂谈",
        "description": "",
        "tag": "何炅,黄磊,周雨彤,向佐,侯明昊,荣梓杉,749局,花学,叶珂,娱乐吃瓜大会,娱乐吃瓜大会7.0"
    },
    {
        "pubdate": "2024-11-04T03:08:55.000",
        "arcurl": "http://www.bilibili.com/video/av113422234551782",
        "author": "一只吐槽圆",
        "title": "一个人一生怎么能有这么多笑话？杨子，内娱之父的爆笑爹生！【杨子黄圣依细盘深扒】",
        "typename": "娱乐杂谈",
        "description": "",
        "tag": "娱乐吃瓜大会,娱乐吃瓜大会7.0"
    },
    {
        "pubdate": "2024-11-03T11:10:22.000",
        "arcurl": "http://www.bilibili.com/video/av113418644364978",
        "author": "岱川博士",
        "title": "岱川博士: 聊聊《了凡四训》和命运最受争议的几个问题 (值得收藏!)",
        "typename": "社科·法律·心理",
        "description": "-",
        "tag": "哲学,命运,外国人,人文,博士,问题,国学,了凡四训,人生智慧,社会深度报告,资讯直通车5.0"
    },
    {
        "pubdate": "2024-11-03T02:30:00.000",
        "arcurl": "http://www.bilibili.com/video/av113414349259523",
        "author": "开心嘴炮",
        "title": "气得心趴疼！麦学出场谁敢来战？张泉灵差点栽她手上！《再见爱人》高能解说",
        "typename": "娱乐杂谈",
        "description": "全程高能吐槽《再见爱人4》第三期",
        "tag": "吐槽,爆笑,综艺,黄圣依,李行亮,杨子,张泉灵,再见爱人,麦琳,娱乐吃瓜大会,娱乐吃瓜大会7.0"
    },
    {
        "pubdate": "2024-11-01T10:19:23.000",
        "arcurl": "http://www.bilibili.com/video/av113407168610765",
        "author": "刘老师说电影",
        "title": "年度必看！既温暖又好笑，《小巷人家》肯定会爆！",
        "typename": "影视杂谈",
        "description": "放弃了宏大的叙事，把重心聚焦在平凡生活的柴米油盐中。",
        "tag": "解说,闫妮,温情,温暖,蒋欣,暖心,年代剧,小巷人家,友你更好,影视剧中的友情天花板"
    },
    {
        "pubdate": "2024-10-31T11:00:00.000",
        "arcurl": "http://www.bilibili.com/video/av113399870593260",
        "author": "动物园会议",
        "title": "【吃瓜报告】回旋镖、花学侯明昊、搞笑操作频发！近期爆笑吃瓜点评（10月第5期）",
        "typename": "娱乐杂谈",
        "description": "",
        "tag": "杨幂,王一博,花少,侯明昊,花学,单依纯,大梦归离,还是淘宝香,双11上天猫超市,上天猫超市抢茅台"
    },
    {
        "pubdate": "2024-10-31T10:00:00.000",
        "arcurl": "http://www.bilibili.com/video/av113395743393914",
        "author": "小片片说大片",
        "title": "出轨，杀夫，骗警察？这场爆炸谋杀案，真凶已逃脱！印度悬疑片《魅杀》",
        "typename": "影视杂谈",
        "description": "《魅杀》，一部融爱情、犯罪、悬疑为一炉的电影。\n不仅有出轨狗血爱情，还整出不少极限反转。\n看来印度人拍悬疑片，是有点天赋的。",
        "tag": "爱情,印度,反转,悬疑,惊悚,犯罪,魅杀,人人都能聊影视,人人都能聊影视4.0"
    },
    {
        "pubdate": "2024-10-30T11:11:38.000",
        "arcurl": "http://www.bilibili.com/video/av113395709773874",
        "author": "话很多的小姐姐们",
        "title": "近期古偶锐评：全面沦陷！你们就糟心地去吧！",
        "typename": "影视杂谈",
        "description": "本来以为一下子抬上来三部古偶会热闹一点，结果是一部比一部完蛋",
        "tag": "七夜雪,吴谨言,张晚意,古偶,任敏,锦绣安宁,还是淘宝香,春花焰,双11上天猫超市,上天猫超市抢茅台"
    },
    {
        "pubdate": "2024-10-30T10:00:54.000",
        "arcurl": "http://www.bilibili.com/video/av113395726621108",
        "author": "高天天天翔",
        "title": "我终于找到了抛弃我的妈妈，但她有了新家庭….",
        "typename": "短片",
        "description": "-",
        "tag": "原创,短片,妈妈,剧情向,亲情,新影力短片大赛"
    }
]